{
  "skills": [
    {
      "iconClass": "devicon-vscode-plain",
      "iconTitle": "vscode"
    },
    {
      "iconClass": "devicon-html5-plain",
      "iconTitle": "html5"
    },
    {
      "iconClass": "devicon-css3-plain",
      "iconTitle": "css3"
    },
    {
      "iconClass": "devicon-sass-original",
      "iconTitle": "sass"
    },
    {
      "iconClass": "devicon-tailwindcss-original",
      "iconTitle": "tailwindcss"
    },
    {
      "iconClass": "devicon-vitejs-plain",
      "iconTitle": "vite"
    },
    {
      "iconClass": "devicon-javascript-plain",
      "iconTitle": "javascript"
    },
    {
      "iconClass": "devicon-typescript-plain",
      "iconTitle": "typescript"
    },
    {
      "iconClass": "devicon-gulp-plain",
      "iconTitle": "gulp"
    },
    {
      "iconClass": "devicon-vercel-original",
      "iconTitle": "vercel"
    },
    {
      "iconClass": "devicon-react-original",
      "iconTitle": "react"
    },
    {
      "iconClass": "devicon-nextjs-plain",
      "iconTitle": "nextjs"
    },
    {
      "iconClass": "devicon-supabase-plain",
      "iconTitle": "supabase"
    },
    {
      "iconClass": "devicon-github-original",
      "iconTitle": "GitHub"
    },
    {
      "iconClass": "devicon-illustrator-plain",
      "iconTitle": "Illustrator"
    },
    {
      "iconClass": "devicon-photoshop-plain",
      "iconTitle": "Photoshop"
    },
    {
      "iconClass": "devicon-figma-plain",
      "iconTitle": "Figma"
    },
    {
      "iconClass": "devicon-astro-plain",
      "iconTitle": "Astro"
    },
    {
      "iconClass": "devicon-amazonwebservices-plain-wordmark",
      "iconTitle": "AWS"
    }
  ],
  "works": [
    {
      "id": 1,
      "title": "The wild Oasis",
      "src": "https://ik.imagekit.io/milanz/milanzivanov_com/next-portfolio-projects/two_hFaaMZMR7.webp",
      "linkSrc": "https://wild-oasis-next-ouec4f5g4-milanzivanovs-projects.vercel.app/",
      "body": "This is a next.js project with typescript, tailwindcss & supabase. It is still in development. Also I'm using this project to practice and learn next.js and typescript.",
      "projectTime": "In development",
      "author": "Milan",
      "technologiesUsed": [
        {
          "svgIcon": "devicon-nextjs-plain"
        },
        {
          "svgIcon": "devicon-typescript-plain"
        },
        {
          "svgIcon": "devicon-supabase-plain"
        },
        {
          "svgIcon": "devicon-tailwindcss-original"
        }
      ]
    },
    {
      "id": 2,
      "title": "Kulturni heroj",
      "src": "https://ik.imagekit.io/milanz/milanzivanov_com/next-portfolio-projects/Kulturni-heroj__flHR7GEEA.webp",
      "linkSrc": "https://kulturniheroj.org",
      "body": "Kulturni Heroj, or Cultural Hero, is a web blog portal dedicated to cultural topics in Serbia. It features a login system and a dashboard that allows administrators to manage content. ",
      "projectTime": "The project is still under development...",
      "author": "Milan",
      "technologiesUsed": [
        {
          "svgIcon": "devicon-html5-plain"
        },
        {
          "svgIcon": "devicon-tailwindcss-original"
        },
        {
          "svgIcon": "devicon-react-original"
        },
        {
          "svgIcon": "devicon-supabase-plain"
        },
        {
          "svgIcon": "devicon-vitejs-plain"
        }
      ]
    },
    {
      "id": 3,
      "title": "Today I learned",
      "src": "https://ik.imagekit.io/milanz/milanzivanov_com/next-portfolio-projects/Today-I-Learned_AXCU7ZUJZ.webp",
      "linkSrc": "https://todayilearned-milan.netlify.app/",
      "body": "Crash course build a full-stack web app in a weekend! In this project for backend I used supabase and for frontend I used react and vite.",
      "projectTime": "Time spent on this project is two weekends.",
      "author": "Milan",
      "technologiesUsed": [
        {
          "svgIcon": "devicon-react-original"
        },
        {
          "svgIcon": "devicon-vitejs-plain"
        },
        {
          "svgIcon": "devicon-supabase-plain"
        },
        {
          "svgIcon": "devicon-html5-plain"
        },
        {
          "svgIcon": "devicon-css3-plain"
        }
      ]
    },
    {
      "id": 4,
      "title": "Comfy store app",
      "src": "https://ik.imagekit.io/milanz/milanzivanov_com/next-portfolio-projects/Comfy-store-TS_KWown2DNe.webp",
      "linkSrc": "https://comfy-store-mz.netlify.app/",
      "body": "Udemy course that I bought for learning react with typescript. Main goal was to learn react and it was a great experience.",
      "projectTime": "Time spent on this project is one month.",
      "author": "Milan",
      "technologiesUsed": [
        {
          "svgIcon": "devicon-react-original"
        },
        {
          "svgIcon": "devicon-typescript-plain"
        },
        {
          "svgIcon": "devicon-html5-plain"
        },
        {
          "svgIcon": "devicon-css3-plain"
        }
      ]
    },
    {
      "id": 5,
      "title": "Movies app",
      "src": "https://ik.imagekit.io/milanz/milanzivanov_com/next-portfolio-projects/Movie-Interstellar_GsRqTP5av.webp",
      "linkSrc": "https://usepopcornclone.netlify.app/",
      "body": "I'm practicing React by making this project. Started from basic features and now I'm working on more advanced features.",
      "projectTime": "Time spent on this project is two month.",
      "author": "Milan",
      "technologiesUsed": [
        {
          "svgIcon": "devicon-react-original"
        },
        {
          "svgIcon": "devicon-vitejs-plain"
        },
        {
          "svgIcon": "devicon-html5-plain"
        },
        {
          "svgIcon": "devicon-css3-plain"
        }
      ]
    },

    {
      "id": 6,
      "title": "Personal site old",
      "src": "https://ik.imagekit.io/milanz/milanzivanov_com/next-portfolio-projects/Milan-Zivanov-Front-end-Developer_b1X3RRkHU.webp",
      "linkSrc": "https://milanzivanov.netlify.app",
      "body": "This is my old personal website, which I created using HTML, CSS, JavaScript and Vite. I made it to practice my skills and to show my work and skills. Frontend and design is mede by me.",
      "projectTime": "One month",
      "author": "Milan",
      "technologiesUsed": [
        {
          "svgIcon": "devicon-vitejs-plain"
        },
        {
          "svgIcon": "devicon-html5-plain"
        },
        {
          "svgIcon": "devicon-css3-plain"
        }
      ]
    },
    {
      "id": 7,
      "title": "Fake shop app",
      "src": "https://ik.imagekit.io/milanz/milanzivanov_com/next-portfolio-projects/Fake-shop-app_UMVkSPDAj.webp",
      "linkSrc": "https://fakeshop123.netlify.app/",
      "body": "Final task from javascript-react course summer 2024. This is fake shop app created with react and vite.",
      "projectTime": "One week",
      "author": "Milan",
      "technologiesUsed": [
        {
          "svgIcon": "devicon-vitejs-plain"
        },
        {
          "svgIcon": "devicon-react-original"
        },
        {
          "svgIcon": "devicon-html5-plain"
        },
        {
          "svgIcon": "devicon-tailwindcss-original"
        }
      ]
    }
  ]
}
